metabase/__init__.py
metabase/exception.py
metabase/serializer.py
metabase/service/__init__.py
metabase/service/http_service.py
metabase/service/metabase_service.py
MetabaseRestClient-0.0.5.dist-info/LICENSE
MetabaseRestClient-0.0.5.dist-info/METADATA
MetabaseRestClient-0.0.5.dist-info/WHEEL
MetabaseRestClient-0.0.5.dist-info/top_level.txt
MetabaseRestClient-0.0.5.dist-info/RECORD
